bkit/__init__.py
bkit/analysis/__init__.py
bkit/analysis/sentences.py
bkit/analysis/words.py
bkit/coref/__init__.py
bkit/coref/_helpers.py
bkit/coref/_infer.py
bkit/dependency/__init__.py
bkit/dependency/_helpers.py
bkit/dependency/_infer.py
bkit/lemmatizer/__init__.py
bkit/lemmatizer/_lemmatize.py
bkit/lemmatizer/data/dictionary.pkl
bkit/lemmatizer/data/markers.pkl
bkit/lemmatizer/data/suffixes.pkl
bkit/lemmatizer/data/bnlp_models/bn_pos.pkl
bkit/lemmatizer/utils/__init__.py
bkit/lemmatizer/utils/lemmatize.py
bkit/lemmatizer/utils/pos.py
bkit/ner/__init__.py
bkit/ner/_helpers.py
bkit/ner/_infer.py
bkit/pos/__init__.py
bkit/pos/_helpers.py
bkit/pos/_infer.py
bkit/shallow/__init__.py
bkit/shallow/_infer.py
bkit/shallow/_models/__init__.py
bkit/shallow/_models/chart_helper.pyx
bkit/shallow/_models/decoder.py
bkit/shallow/_models/embeddings.py
bkit/shallow/_models/encoder.py
bkit/shallow/_models/span_attentions.py
bkit/shallow/dataloaders/__init__.py
bkit/shallow/dataloaders/trees.py
bkit/shallow/dataloaders/vocabulary.py
bkit/shallow/utils/__init__.py
bkit/shallow/utils/_utils.py
bkit/shallow/utils/attutil.py
bkit/shallow/utils/nkutil.py
bkit/shallow/utils/token.py
bkit/shallow/utils/transliterate.py
bkit/stemmer/__init__.py
bkit/stemmer/_simple_stemmer.py
bkit/stemmer/data/words.pkl
bkit/tokenizer/__init__.py
bkit/tokenizer/_sentence_tokenization.py
bkit/tokenizer/_word_tokenization.py
bkit/transform/__init__.py
bkit/transform/cleaning.py
bkit/transform/normalizing.py
bkit/utils/__init__.py
bkit/utils/_download.py
bkit/utils/_files_and_dirs.py
bkit/utils/_models.py
bkit/utils/_text.py
bkit/utils/_util_functions.py
tests/test_analysis.py
tests/test_cleaning.py
tests/test_normalization.py
bkit-0.0.9.dist-info/METADATA
bkit-0.0.9.dist-info/WHEEL
bkit-0.0.9.dist-info/top_level.txt
bkit-0.0.9.dist-info/RECORD
