Metadata-Version: 2.2
Name: bkit
Version: 0.0.9
Summary: A python tool for Bangla text processing
Author-email: banglagov <manage.bangla@gmail.com>
Project-URL: Homepage, https://github.com/giga-tech/bangla-text-processing-kit
Keywords: bangla kit,bangla text processing,banpipeline,ner,pos,shallow parsing,dependency parsing
Classifier: Programming Language :: Python :: 3
Classifier: License :: OSI Approved :: MIT License
Classifier: Operating System :: OS Independent
Requires-Python: >=3.7
Requires-Dist: regex
Provides-Extra: lemma
Requires-Dist: bnlp-toolkit; extra == "lemma"
Provides-Extra: all
Requires-Dist: torch<2.6,>=1.13; extra == "all"
Requires-Dist: bnlp-toolkit; extra == "all"
Requires-Dist: transformers[sentencepiece]==4.28.0; extra == "all"
Requires-Dist: onnxruntime<2.0,>=1.20.1; extra == "all"
Requires-Dist: spacy<4.0,>=3.8.4; extra == "all"
Requires-Dist: datasets; extra == "all"
Requires-Dist: gdown; extra == "all"
Requires-Dist: cython; extra == "all"
Requires-Dist: pyhocon; extra == "all"
Requires-Dist: numpy; extra == "all"
Requires-Dist: segtok; extra == "all"
